dropbox_updater/__init__.py
dropbox_updater/logger.py
dropbox_updater/updater.py
dropbox_updater-1.0.7.dist-info/LICENSE
dropbox_updater-1.0.7.dist-info/METADATA
dropbox_updater-1.0.7.dist-info/WHEEL
dropbox_updater-1.0.7.dist-info/top_level.txt
dropbox_updater-1.0.7.dist-info/RECORD
