Metadata-Version: 2.1
Name: dropbox-updater
Version: 1.0.7
Summary: Module to update python script using dropbox api
Home-page: https://github.com/sandbox-pokhara/dropbox-updater
Author: Pradish Bijukchhe
Author-email: pradishbijukchhe@gmail.com
License: UNKNOWN
Project-URL: Bug Tracker, https://github.com/sandbox-pokhara/dropbox-updater/issues
Platform: UNKNOWN
Classifier: Programming Language :: Python :: 3
Classifier: License :: OSI Approved :: MIT License
Requires-Python: >=3.6
License-File: LICENSE
Requires-Dist: requests
Requires-Dist: requests-futures
